LICENSE
pfcli/__init__.py
pfcli/__main__.py
pfcli/bootstrap/__init__.py
pfcli/bootstrap/backend_factory.py
pfcli/bootstrap/cli_factory.py
pfcli/bootstrap/printer_factory.py
pfcli/config.py
pfcli/consts.py
pfcli/domain/__init__.py
pfcli/domain/firmware/__init__.py
pfcli/domain/firmware/api.py
pfcli/domain/firmware/entities.py
pfcli/domain/info.py
pfcli/domain/printers/printers.py
pfcli/domain/unbound/__init__.py
pfcli/domain/unbound/api.py
pfcli/domain/unbound/entities.py
pfcli/environment.py
pfcli/plugins/__init__.py
pfcli/plugins/backends/__init__.py
pfcli/plugins/backends/xmlrpc/__init__.py
pfcli/plugins/backends/xmlrpc/command_runner.py
pfcli/plugins/backends/xmlrpc/firmware.py
pfcli/plugins/backends/xmlrpc/unbound.py
pfcli/plugins/printers/__init__.py
pfcli/plugins/printers/json.py
pfcli/plugins/printers/text.py
pfcli/py.typed
pfcli/shared/helpers.py
pfcli/shared/sanitizers.py
pfcli/shared/validators.py
pfcli-0.2.0.dist-info/LICENSE
pfcli-0.2.0.dist-info/METADATA
pfcli-0.2.0.dist-info/WHEEL
pfcli-0.2.0.dist-info/entry_points.txt
pfcli-0.2.0.dist-info/RECORD
