Metadata-Version: 2.1
Name: pfcli
Version: 0.2.0
Summary: A CLI for managing pfSense configurations
Home-page: https://pfcli.readthedocs.io
License: MPL-2.0
Keywords: cli,configuration,dns,networking,pfsense,unbound
Author: Ely Deckers
Maintainer: Ely Deckers
Requires-Python: >=3.11
Classifier: Development Status :: 4 - Beta
Classifier: Intended Audience :: Developers
Classifier: Intended Audience :: System Administrators
Classifier: License :: OSI Approved
Classifier: License :: OSI Approved :: Mozilla Public License 2.0 (MPL 2.0)
Classifier: Programming Language :: Python :: 3
Classifier: Programming Language :: Python :: 3.11
Classifier: Programming Language :: Python :: 3.12
Classifier: Programming Language :: Python :: 3.13
Classifier: Topic :: System :: Networking :: Firewalls
Classifier: Topic :: Utilities
Requires-Dist: click (>=8.1.7,<9.0.0)
Requires-Dist: defusedxml (>=0.7,<0.8)
Project-URL: Documentation, https://github.com/edeckers/pfcli
Project-URL: Repository, https://github.com/edeckers/pfcli.git
